ophyon/__init__.py
ophyon-0.0.1.dist-info/LICENSE
ophyon-0.0.1.dist-info/METADATA
ophyon-0.0.1.dist-info/WHEEL
ophyon-0.0.1.dist-info/top_level.txt
ophyon-0.0.1.dist-info/RECORD
