Metadata-Version: 2.1
Name: ophyon
Version: 0.0.1
Summary: for the tea ophyon static site builder
Home-page: https://github.com/load1n9/tea
Author: loading...
Author-email: loadin0000@example.com
License: UNKNOWN
Platform: UNKNOWN
Classifier: Programming Language :: Python :: 3
Classifier: License :: OSI Approved :: MIT License
Classifier: Operating System :: OS Independent
Requires-Python: >=3.6
